panda_logger/__init__.py
panda_logger/decorater.py
panda_logger/logger.py
panda_logger/test.py
panda_logger-0.2.dist-info/LICENSE
panda_logger-0.2.dist-info/METADATA
panda_logger-0.2.dist-info/WHEEL
panda_logger-0.2.dist-info/top_level.txt
panda_logger-0.2.dist-info/RECORD
